odoo/addons/stock_financial_risk/README.rst
odoo/addons/stock_financial_risk/__init__.py
odoo/addons/stock_financial_risk/__manifest__.py
odoo/addons/stock_financial_risk/i18n/ca.po
odoo/addons/stock_financial_risk/i18n/de.po
odoo/addons/stock_financial_risk/i18n/es.po
odoo/addons/stock_financial_risk/i18n/es_AR.po
odoo/addons/stock_financial_risk/i18n/es_MX.po
odoo/addons/stock_financial_risk/i18n/fi.po
odoo/addons/stock_financial_risk/i18n/fr.po
odoo/addons/stock_financial_risk/i18n/gl.po
odoo/addons/stock_financial_risk/i18n/hr.po
odoo/addons/stock_financial_risk/i18n/it.po
odoo/addons/stock_financial_risk/i18n/pt.po
odoo/addons/stock_financial_risk/i18n/pt_BR.po
odoo/addons/stock_financial_risk/i18n/ro.po
odoo/addons/stock_financial_risk/i18n/sl.po
odoo/addons/stock_financial_risk/i18n/tr.po
odoo/addons/stock_financial_risk/i18n/tr_TR.po
odoo/addons/stock_financial_risk/i18n/vi_VN.po
odoo/addons/stock_financial_risk/i18n/zh_CN.po
odoo/addons/stock_financial_risk/models/__init__.py
odoo/addons/stock_financial_risk/models/stock.py
odoo/addons/stock_financial_risk/readme/CONTRIBUTORS.rst
odoo/addons/stock_financial_risk/readme/DESCRIPTION.rst
odoo/addons/stock_financial_risk/readme/USAGE.rst
odoo/addons/stock_financial_risk/static/description/index.html
odoo/addons/stock_financial_risk/tests/__init__.py
odoo/addons/stock_financial_risk/tests/test_stock_financial_risk.py
odoo12_addon_stock_financial_risk-12.0.1.0.0.dist-info/METADATA
odoo12_addon_stock_financial_risk-12.0.1.0.0.dist-info/RECORD
odoo12_addon_stock_financial_risk-12.0.1.0.0.dist-info/WHEEL
odoo12_addon_stock_financial_risk-12.0.1.0.0.dist-info/top_level.txt
